{
	"nytimes" : "#story",
	"cnn" : "#body-text",
	"huffingtonpost" : ".component.entry-component",
	"medium" : ".postArticle-content",
	"slate" : ".main .content",
	"washingtonpost" : "#article-body",
	"propublica" : "article .bodytext",
	"npr" : "#storytext",
	"newyorker" : "#articleBody",
	"theatlantic" : "#article",
	"nymag" : ".story",
	"buzzfeed" : "#buzz_sub_buzz",
	"bostonglobe" : ".article-text",
	"latimes" : ".trb_mainContent",
	"theverge" : ".m-entry__content",
	"theguardian" : ".content__main",
	"qz" : ".item-body",
	"rollingstone" : ".primary",
	"politico" : ".story-text",
	"newrepublic" : ".body.text",
	"gq" : ".body-text",
	"outsideonline" : ".post-entry",
	"sbnation" : "#feature-body .main-div",

	"default" : [
		"#article",
		"#story",
		"#articleBody",
		"#storyBody",
		".story",
		".article",
		".body",
		"article"
	]
}